outcome/__init__.py
outcome/_impl.py
outcome/_util.py
outcome/_version.py
outcome/py.typed
outcome-1.3.0.dist-info/LICENSE
outcome-1.3.0.dist-info/LICENSE.APACHE2
outcome-1.3.0.dist-info/LICENSE.MIT
outcome-1.3.0.dist-info/METADATA
outcome-1.3.0.dist-info/WHEEL
outcome-1.3.0.dist-info/top_level.txt
outcome-1.3.0.dist-info/RECORD
