Metadata-Version: 2.1
Name: outcome
Version: 1.3.0
Summary: Capture the outcome of Python function calls.
Home-page: https://github.com/python-trio/outcome
Author: Frazer McLean
Author-email: frazer@frazermclean.co.uk
License: MIT OR Apache-2.0
Project-URL: Documentation, https://outcome.readthedocs.io/en/latest/
Project-URL: Chat, https://gitter.im/python-trio/general
Keywords: result
Classifier: Development Status :: 5 - Production/Stable
Classifier: Framework :: Trio
Classifier: Intended Audience :: Developers
Classifier: License :: OSI Approved :: MIT License
Classifier: License :: OSI Approved :: Apache Software License
Classifier: Operating System :: POSIX :: Linux
Classifier: Operating System :: MacOS :: MacOS X
Classifier: Operating System :: Microsoft :: Windows
Classifier: Programming Language :: Python :: 3.7
Classifier: Programming Language :: Python :: 3.8
Classifier: Programming Language :: Python :: 3.9
Classifier: Programming Language :: Python :: 3.10
Classifier: Programming Language :: Python :: Implementation :: CPython
Classifier: Programming Language :: Python :: Implementation :: PyPy
Requires-Python: >=3.7
License-File: LICENSE
License-File: LICENSE.APACHE2
License-File: LICENSE.MIT
